neurec/__init__.py
neurec/neurec.py
neurec/data/Dataset.py
neurec/data/GivenData.py
neurec/data/HoldOutDataSplitter.py
neurec/data/LeaveOneOutDataSplitter.py
neurec/data/__init__.py
neurec/data/models.py
neurec/data/properties.py
neurec/dataset/Ciao.rating
neurec/dataset/Ciao.trust
neurec/dataset/__init__.py
neurec/dataset/ml-100k.rating
neurec/dataset/ml-1m.test.rating
neurec/dataset/ml-1m.train.rating
neurec/dataset/ml100k_saved_model.pkl
neurec/evaluation/Evaluate.py
neurec/evaluation/__init__.py
neurec/evaluation/foldout/AUC.py
neurec/evaluation/foldout/FoldOutEvaluate.py
neurec/evaluation/foldout/MAP.py
neurec/evaluation/foldout/MRR.py
neurec/evaluation/foldout/NDCG.py
neurec/evaluation/foldout/Precision.py
neurec/evaluation/foldout/Recall.py
neurec/evaluation/foldout/__init__.py
neurec/evaluation/leaveoneout/ARHR.py
neurec/evaluation/leaveoneout/AUC.py
neurec/evaluation/leaveoneout/HR.py
neurec/evaluation/leaveoneout/LeaveOneOutEvaluate.py
neurec/evaluation/leaveoneout/NDCG.py
neurec/evaluation/leaveoneout/__init__.py
neurec/model/AbstractRecommender.py
neurec/model/__init__.py
neurec/model/item_ranking/APR.py
neurec/model/item_ranking/CDAE.py
neurec/model/item_ranking/CFGAN.py
neurec/model/item_ranking/ConvNCF.py
neurec/model/item_ranking/DAE.py
neurec/model/item_ranking/DMF.py
neurec/model/item_ranking/DeepICF.py
neurec/model/item_ranking/FISM.py
neurec/model/item_ranking/IRGAN.py
neurec/model/item_ranking/JCA.py
neurec/model/item_ranking/MF.py
neurec/model/item_ranking/MLP.py
neurec/model/item_ranking/MultiDAE.py
neurec/model/item_ranking/MultiVAE.py
neurec/model/item_ranking/NAIS.py
neurec/model/item_ranking/NGCF.py
neurec/model/item_ranking/NeuMF.py
neurec/model/item_ranking/SBPR.py
neurec/model/item_ranking/SpectralCF.py
neurec/model/item_ranking/WRMF.py
neurec/model/item_ranking/__init__.py
neurec/model/seq_ranking/FPMC.py
neurec/model/seq_ranking/FPMCplus.py
neurec/model/seq_ranking/HRM.py
neurec/model/seq_ranking/NPE.py
neurec-1.0.0.dist-info/LICENSE
neurec-1.0.0.dist-info/METADATA
neurec-1.0.0.dist-info/WHEEL
neurec-1.0.0.dist-info/top_level.txt
neurec-1.0.0.dist-info/RECORD
