Metadata-Version: 2.1
Name: neurec
Version: 1.0.0
Summary: An open source neural recommender library
Home-page: https://github.com/wubinzzu/NeuRec.git
Author: Jonathan Staniforth
Author-email: jonathanstaniforth@gmail.com
License: UNKNOWN
Platform: UNKNOWN
Classifier: Programming Language :: Python :: 3
Classifier: License :: OSI Approved :: MIT License
Classifier: Operating System :: OS Independent
Requires-Python: >=3.5
